sengled/__init__.py
sengled/sengled.py
sengled_client-0.0.2.dist-info/LICENSE
sengled_client-0.0.2.dist-info/METADATA
sengled_client-0.0.2.dist-info/WHEEL
sengled_client-0.0.2.dist-info/top_level.txt
sengled_client-0.0.2.dist-info/RECORD
