Metadata-Version: 2.1
Name: sengled-client
Version: 0.0.2
Summary: A simple python API client to control Sengled smart devices
Home-page: https://github.com/vroy/python-sengled-client
Author: Vincent Roy
Author-email: vincentroy8@gmail.com
License: UNKNOWN
Platform: UNKNOWN
Classifier: Programming Language :: Python :: 3
Classifier: License :: OSI Approved :: MIT License
Classifier: Operating System :: OS Independent
Requires-Python: >=3.6
Requires-Dist: requests (>=2.22.0)
